MANIFEST.in
requirements.txt
setup.cfg
setup.py
accessall/__init__.py
accessall/__main__.py
accessall/accessall.py
accessall.egg-info/PKG-INFO
accessall.egg-info/SOURCES.txt
accessall.egg-info/dependency_links.txt
accessall.egg-info/entry_points.txt
accessall.egg-info/requires.txt
accessall.egg-info/top_level.txt