Metadata-Version: 1.0
Name: accessall
Version: 1.4
Summary: Google Music command line tool.
Home-page: https://github.com/Raynes/accessall
Author: Anthony Grimes
Author-email: UNKNOWN
License: MIT
Platform: UNKNOWN
